dateutil_gorman/__init__.py
dateutil_gorman/constants.py
dateutil_gorman/conversion.py
dateutil_gorman/parser.py
dateutil_gorman/types.py
dateutil_gorman-0.1.2.dist-info/METADATA
dateutil_gorman-0.1.2.dist-info/WHEEL
dateutil_gorman-0.1.2.dist-info/RECORD
