Metadata-Version: 2.4
Name: dateutil-gorman
Version: 0.1.2
Summary: A Python library for the Gorman Calendar
Project-URL: Homepage, https://github.com/BGarber42/dateutil_gorman
Project-URL: Issues, https://github.com/BGarber42/dateutil_gorman/issues
Author-email: Brent Garber <me@bgarber.work>
License: MIT
Classifier: Development Status :: 3 - Alpha
Classifier: Intended Audience :: Developers
Classifier: License :: OSI Approved :: MIT License
Classifier: Programming Language :: Python :: 3
Classifier: Programming Language :: Python :: 3.10
Classifier: Programming Language :: Python :: 3.11
Classifier: Programming Language :: Python :: 3.12
Requires-Python: >=3.10
Provides-Extra: dev
Requires-Dist: mypy>=1.0.0; extra == 'dev'
Requires-Dist: pytest-mock>=3.10.0; extra == 'dev'
Requires-Dist: pytest>=7.0.0; extra == 'dev'
Requires-Dist: ruff>=0.1.0; extra == 'dev'
